setup.cfg
setup.py
./ipcat/__init__.py
./ipcat/analysis.py
./ipcat/app.py
./ipcat/common.py
./ipcat/config.py
./ipcat/control.py
./ipcat/gui.py
./ipcat/guiComponents.py
./ipcat/handlers.py
./ipcat/io.py
./ipcat/model.py
./ipcat/test.py
./ipcat/vcontrol.py
./ipcat/view.py
./ipcat/vmodel.py
ipcat.egg-info/PKG-INFO
ipcat.egg-info/SOURCES.txt
ipcat.egg-info/dependency_links.txt
ipcat.egg-info/requires.txt
ipcat.egg-info/top_level.txt