Metadata-Version: 2.1
Name: ipcat
Version: 0.0.0
Summary: Image processing testing
Home-page: UNKNOWN
Author: Takanori Kono
License: UNKNOWN
Platform: UNKNOWN
Requires-Python: >=3.7
